whitemagic_client/__init__.py
whitemagic_client/client.py
whitemagic_client/exceptions.py
whitemagic_client/types.py
whitemagic_client-2.2.7.dist-info/METADATA
whitemagic_client-2.2.7.dist-info/WHEEL
whitemagic_client-2.2.7.dist-info/licenses/LICENSE
whitemagic_client-2.2.7.dist-info/RECORD
