Metadata-Version: 2.4
Name: whitemagic-client
Version: 2.2.7
Summary: Official Python SDK for WhiteMagic - Memory infrastructure for AI agents
Project-URL: Homepage, https://github.com/lbailey94/whitemagic
Project-URL: Documentation, https://github.com/lbailey94/whitemagic#readme
Project-URL: Repository, https://github.com/lbailey94/whitemagic.git
Project-URL: Issues, https://github.com/lbailey94/whitemagic/issues
Author-email: WhiteMagic Team <support@whitemagic.dev>
License: MIT License
License-File: LICENSE
Keywords: agents,ai,api-client,memory,sdk,whitemagic
Classifier: Development Status :: 4 - Beta
Classifier: Intended Audience :: Developers
Classifier: License :: OSI Approved :: MIT License
Classifier: Programming Language :: Python :: 3
Classifier: Programming Language :: Python :: 3.9
Classifier: Programming Language :: Python :: 3.10
Classifier: Programming Language :: Python :: 3.11
Classifier: Programming Language :: Python :: 3.12
Requires-Python: >=3.9
Requires-Dist: httpx>=0.25.0
Requires-Dist: pydantic>=2.0.0
Provides-Extra: dev
Requires-Dist: black>=23.0.0; extra == 'dev'
Requires-Dist: mypy>=1.0.0; extra == 'dev'
Requires-Dist: pytest-asyncio>=0.21.0; extra == 'dev'
Requires-Dist: pytest>=7.0.0; extra == 'dev'
